ssl_tunnel/__init__.py
ssl_tunnel/main.py
ssl_tunnel/core/__init__.py
ssl_tunnel/core/cli.py
ssl_tunnel/core/flow_and_route_manager.py
ssl_tunnel/core/global_resources.py
ssl_tunnel/core/network_protocol.py
ssl_tunnel/core/ssl_client.py
ssl_tunnel/core/ssl_server.py
ssl_tunnel/core/tun_interface.py
ssl_tunnel/utils/__init__.py
ssl_tunnel/utils/certificate_management.py
ssl_tunnel/utils/logging_config.py
ssl_tunnel/utils/validators.py
ssl_tunnel-0.4.dist-info/METADATA
ssl_tunnel-0.4.dist-info/WHEEL
ssl_tunnel-0.4.dist-info/entry_points.txt
ssl_tunnel-0.4.dist-info/top_level.txt
ssl_tunnel-0.4.dist-info/RECORD
