Metadata-Version: 2.1
Name: ssl-tunnel
Version: 0.4
Summary: SSL Tunnel Tool for secure and flexible network tunneling
Author: Simon Rho
Author-email: srho@juniper.net
Requires-Python: >=3.7
Requires-Dist: pyroute2
Requires-Dist: cryptography
Requires-Dist: requests
Requires-Dist: watchdog
Requires-Dist: cffi
